moonshine_voice/__init__.py
moonshine_voice/download.py
moonshine_voice/download_file.py
moonshine_voice/errors.py
moonshine_voice/intent_recognizer.py
moonshine_voice/libmoonshine.dylib
moonshine_voice/libmoonshine.so
moonshine_voice/libonnxruntime.1.23.2.dylib
moonshine_voice/mic_transcriber.py
moonshine_voice/moonshine_api.py
moonshine_voice/transcriber.py
moonshine_voice/utils.py
moonshine_voice/assets/beckett.wav
moonshine_voice/assets/two_cities.wav
moonshine_voice/assets/tiny-en/.DS_Store
moonshine_voice/assets/tiny-en/decoder_model_merged.ort
moonshine_voice/assets/tiny-en/encoder_model.ort
moonshine_voice/assets/tiny-en/tokenizer.bin
moonshine_voice.libs/libonnxruntime-13ab8084.so.1
moonshine_voice-0.0.43.dist-info/METADATA
moonshine_voice-0.0.43.dist-info/WHEEL
moonshine_voice-0.0.43.dist-info/top_level.txt
moonshine_voice-0.0.43.dist-info/RECORD
moonshine_voice-0.0.43.dist-info/licenses/LICENSE
