Metadata-Version: 2.4
Name: moonshine-voice
Version: 0.0.43
Summary: Fast, accurate, on-device AI library for building interactive voice applications
Home-page: https://github.com/moonshine-ai/moonshine
Author: Moonshine AI
License: MIT
Project-URL: Homepage, https://github.com/usefulsensors/moonshine-v2
Project-URL: Documentation, https://github.com/usefulsensors/moonshine-v2
Project-URL: Repository, https://github.com/usefulsensors/moonshine-v2
Project-URL: Issues, https://github.com/usefulsensors/moonshine-v2/issues
Keywords: speech,transcription,voice,ai,on-device,stt
Classifier: Development Status :: 3 - Alpha
Classifier: Intended Audience :: Developers
Classifier: License :: OSI Approved :: MIT License
Classifier: Programming Language :: Python :: 3
Classifier: Programming Language :: Python :: 3.8
Classifier: Programming Language :: Python :: 3.9
Classifier: Programming Language :: Python :: 3.10
Classifier: Programming Language :: Python :: 3.11
Classifier: Programming Language :: Python :: 3.12
Classifier: Topic :: Software Development :: Libraries :: Python Modules
Classifier: Topic :: Multimedia :: Sound/Audio :: Speech
Requires-Python: >=3.8
License-File: LICENSE
Requires-Dist: numpy
Requires-Dist: sounddevice
Requires-Dist: requests
Requires-Dist: tqdm
Requires-Dist: filelock
Requires-Dist: platformdirs
Dynamic: home-page
Dynamic: license-file
Dynamic: requires-python
